stemtokenizer/__init__.py
stemtokenizer/tokenizer.py
stemtokenizer-0.1.dist-info/METADATA
stemtokenizer-0.1.dist-info/WHEEL
stemtokenizer-0.1.dist-info/top_level.txt
stemtokenizer-0.1.dist-info/RECORD
